odoo/addons/stock_picking_orig_dest_link/README.rst
odoo/addons/stock_picking_orig_dest_link/__init__.py
odoo/addons/stock_picking_orig_dest_link/__manifest__.py
odoo/addons/stock_picking_orig_dest_link/hooks.py
odoo/addons/stock_picking_orig_dest_link/i18n/it.po
odoo/addons/stock_picking_orig_dest_link/i18n/stock_picking_orig_dest_link.pot
odoo/addons/stock_picking_orig_dest_link/models/__init__.py
odoo/addons/stock_picking_orig_dest_link/models/stock_picking.py
odoo/addons/stock_picking_orig_dest_link/readme/CONTRIBUTORS.rst
odoo/addons/stock_picking_orig_dest_link/readme/DESCRIPTION.rst
odoo/addons/stock_picking_orig_dest_link/readme/ROADMAP.rst
odoo/addons/stock_picking_orig_dest_link/static/description/icon.png
odoo/addons/stock_picking_orig_dest_link/static/description/index.html
odoo/addons/stock_picking_orig_dest_link/tests/__init__.py
odoo/addons/stock_picking_orig_dest_link/tests/test_stock_picking_orig_dest_link.py
odoo/addons/stock_picking_orig_dest_link/views/stock_picking_views.xml
odoo_addon_stock_picking_orig_dest_link-15.0.1.0.0.5.dist-info/METADATA
odoo_addon_stock_picking_orig_dest_link-15.0.1.0.0.5.dist-info/WHEEL
odoo_addon_stock_picking_orig_dest_link-15.0.1.0.0.5.dist-info/top_level.txt
odoo_addon_stock_picking_orig_dest_link-15.0.1.0.0.5.dist-info/RECORD
